tts_wrapper/__init__.py
tts_wrapper/engines/__init__.py
tts_wrapper/engines/google/__init__.py
tts_wrapper/engines/google/client.py
tts_wrapper/engines/google/google.py
tts_wrapper/engines/google/ssml.py
tts_wrapper/engines/microsoft/__init__.py
tts_wrapper/engines/microsoft/client.py
tts_wrapper/engines/microsoft/microsoft.py
tts_wrapper/engines/microsoft/ssml.py
tts_wrapper/engines/pico/__init__.py
tts_wrapper/engines/pico/client.py
tts_wrapper/engines/pico/pico.py
tts_wrapper/engines/polly/__init__.py
tts_wrapper/engines/polly/client.py
tts_wrapper/engines/polly/polly.py
tts_wrapper/engines/polly/ssml.py
tts_wrapper/engines/sapi/__init__.py
tts_wrapper/engines/sapi/client.py
tts_wrapper/engines/sapi/sapi.py
tts_wrapper/engines/utils.py
tts_wrapper/engines/watson/__init__.py
tts_wrapper/engines/watson/client.py
tts_wrapper/engines/watson/ssml.py
tts_wrapper/engines/watson/watson.py
tts_wrapper/exceptions.py
tts_wrapper/ssml/__init__.py
tts_wrapper/ssml/ssml_node.py
tts_wrapper/ssml/ssml_root.py
tts_wrapper/tts.py
tts_wrapper-0.8.0.dist-info/LICENSE
tts_wrapper-0.8.0.dist-info/WHEEL
tts_wrapper-0.8.0.dist-info/METADATA
tts_wrapper-0.8.0.dist-info/RECORD
