Metadata-Version: 2.1
Name: tts-wrapper
Version: 0.8.0
Summary: TTS-Wrapper makes it easier to use text-to-speech APIs by providing a unified and easy-to-use interface.
Home-page: https://github.com/mediatechlab/tts-wrapper
License: MIT
Keywords: tts,text-to-speech,speech synthesis,polly,sapi
Author: Giulio Bottari
Author-email: giuliobottari@gmail.com
Requires-Python: >=3.8,<4.0
Classifier: License :: OSI Approved :: MIT License
Classifier: Programming Language :: Python :: 3
Classifier: Programming Language :: Python :: 3.10
Classifier: Programming Language :: Python :: 3.8
Classifier: Programming Language :: Python :: 3.9
Provides-Extra: google
Provides-Extra: microsoft
Provides-Extra: polly
Provides-Extra: sapi
Provides-Extra: watson
Requires-Dist: boto3 (>=1.24.34,<2.0.0); extra == "polly"
Requires-Dist: google-cloud-texttospeech (>=2.11.1,<3.0.0); extra == "google"
Requires-Dist: ibm-watson (>=6.0.0,<7.0.0); extra == "watson"
Requires-Dist: pyttsx3 (>=2.90,<3.0); extra == "sapi"
Requires-Dist: requests (>=2.28.0,<3.0.0); extra == "microsoft"
Project-URL: Bug Tracker, https://github.com/mediatechlab/tts-wrapper/issues
Project-URL: Documentation, https://github.com/mediatechlab/tts-wrapper
Project-URL: Repository, https://github.com/mediatechlab/tts-wrapper
